cola/__init__.py
cola/annotations.py
cola/fns.py
cola/version.py
cola/backends/__init__.py
cola/backends/backends.py
cola/backends/jax_fns.py
cola/backends/np_fns.py
cola/backends/torch_fns.py
cola/linalg/__init__.py
cola/linalg/algorithm_base.py
cola/linalg/decompositions/__init__.py
cola/linalg/decompositions/arnoldi.py
cola/linalg/decompositions/decompositions.py
cola/linalg/decompositions/lanczos.py
cola/linalg/eig/__init__.py
cola/linalg/eig/eigs.py
cola/linalg/eig/iram.py
cola/linalg/eig/lobpcg.py
cola/linalg/eig/power_iteration.py
cola/linalg/inverse/__init__.py
cola/linalg/inverse/cg.py
cola/linalg/inverse/gmres.py
cola/linalg/inverse/inv.py
cola/linalg/inverse/pinv.py
cola/linalg/logdet/__init__.py
cola/linalg/logdet/logdet.py
cola/linalg/trace/__init__.py
cola/linalg/trace/diag_trace.py
cola/linalg/trace/diagonal_estimation.py
cola/linalg/unary/__init__.py
cola/linalg/unary/unary.py
cola/ops/__init__.py
cola/ops/operator_base.py
cola/ops/operators.py
cola/utils/__init__.py
cola/utils/custom_autodiff.py
cola/utils/jax_tqdm.py
cola/utils/torch_tqdm.py
cola/utils/utils_for_tests.py
cola/utils/utils_linalg.py
cola_ml-0.0.7.dist-info/licenses/LICENSE
cola_ml-0.0.7.dist-info/METADATA
cola_ml-0.0.7.dist-info/WHEEL
cola_ml-0.0.7.dist-info/top_level.txt
cola_ml-0.0.7.dist-info/RECORD
