Metadata-Version: 2.4
Name: cola-ml
Version: 0.0.7
Home-page: https://github.com/wilson-labs/cola
Author: Marc Finzi and Andres Potapczynski
Author-email: maf820@nyu.edu
License: MIT
Keywords: linear algebra,linear ops,sparse,PDE,AI,ML
Classifier: Development Status :: 3 - Alpha
Classifier: Intended Audience :: Developers
Classifier: Intended Audience :: Science/Research
Classifier: Programming Language :: Python :: 3
Classifier: Topic :: Scientific/Engineering :: Artificial Intelligence
Requires-Python: >=3.10
License-File: LICENSE
Requires-Dist: scipy
Requires-Dist: tqdm>=4.38
Requires-Dist: cola-plum-dispatch==0.1.4
Requires-Dist: optree
Provides-Extra: dev
Requires-Dist: pytest; extra == "dev"
Requires-Dist: pytest-cov; extra == "dev"
Requires-Dist: setuptools_scm; extra == "dev"
Requires-Dist: pre-commit; extra == "dev"
Dynamic: author
Dynamic: author-email
Dynamic: classifier
Dynamic: description
Dynamic: description-content-type
Dynamic: home-page
Dynamic: keywords
Dynamic: license
Dynamic: license-file
Dynamic: provides-extra
Dynamic: requires-dist
Dynamic: requires-python
